entiny/__init__.py
entiny/cli.py
entiny/core.py
entiny-0.2.5.dist-info/LICENSE
entiny-0.2.5.dist-info/METADATA
entiny-0.2.5.dist-info/WHEEL
entiny-0.2.5.dist-info/entry_points.txt
entiny-0.2.5.dist-info/RECORD
