Metadata-Version: 2.3
Name: entiny
Version: 0.2.5
Summary: 
Author: Alex Hallam
Author-email: alexhallam6.28@gmail.com
Requires-Python: >=3.11
Classifier: Programming Language :: Python :: 3
Classifier: Programming Language :: Python :: 3.11
Classifier: Programming Language :: Python :: 3.12
Classifier: Programming Language :: Python :: 3.13
Requires-Dist: click (>=8.1.8,<9.0.0)
Requires-Dist: numpy (>=2.2.4,<3.0.0)
Requires-Dist: polars (>=1.25.2,<2.0.0)
Requires-Dist: tqdm (>=4.67.1,<5.0.0)
